CnpChargebackSDK-2.1.4.dist-info/DESCRIPTION.rst
CnpChargebackSDK-2.1.4.dist-info/METADATA
CnpChargebackSDK-2.1.4.dist-info/RECORD
CnpChargebackSDK-2.1.4.dist-info/WHEEL
CnpChargebackSDK-2.1.4.dist-info/entry_points.txt
CnpChargebackSDK-2.1.4.dist-info/metadata.json
CnpChargebackSDK-2.1.4.dist-info/top_level.txt
cnpsdk/__init__.py
cnpsdk/chargeback_document.py
cnpsdk/chargeback_retrieval.py
cnpsdk/chargeback_update.py
cnpsdk/communication.py
cnpsdk/fields_chargeback.py
cnpsdk/utils.py
cnpsdk/version.py
scripts/__init__.py
scripts/cnp_chargeback_sdk_setup.py
