Metadata-Version: 2.0
Name: CnpChargebackSDK
Version: 2.1.4
Summary: Vantiv eCommerce Chargeback SDK
Home-page: https://developer.vantiv.com/community/ecommerce
Author: Vantiv eCommerce
Author-email: SDKSupport@vantiv.com
License: MIT
Platform: UNKNOWN
Classifier: Development Status :: 5 - Production/Stable
Classifier: Intended Audience :: Developers
Classifier: Intended Audience :: System Administrators
Classifier: Intended Audience :: Information Technology
Classifier: License :: OSI Approved :: MIT License
Classifier: Operating System :: OS Independent
Classifier: Programming Language :: Python
Classifier: Programming Language :: Python :: 2
Classifier: Programming Language :: Python :: 2.7
Classifier: Programming Language :: Python :: 3
Classifier: Programming Language :: Python :: 3.4
Classifier: Programming Language :: Python :: 3.5
Classifier: Programming Language :: Python :: 3.6
Classifier: Topic :: Office/Business :: Financial
Classifier: Topic :: Software Development :: Libraries
Classifier: Topic :: Software Development :: Libraries :: Python Modules
Requires-Dist: PyXB (==1.2.6)
Requires-Dist: paramiko (>=1.14.0)
Requires-Dist: requests (>=2.13.0)
Requires-Dist: six (>=1.10.0)
Requires-Dist: xmltodict (>=0.10.2)
Requires-Dist: unittest2 (>=1.1.0)
Requires-Dist: mock
